[
  {
    "title": "HTML",
    "imageSrc": "skills2/html.svg"
  },
  {
    "title": "CSS",
    "imageSrc": "skills2/css.svg"
  },
  {
    "title": "JavaScript",
    "imageSrc": "skills2/javascript.svg"
  },
  {
    "title": "jQuery",
    "imageSrc": "skills2/jquery.svg"
  },
  {
    "title": "Sass/SCSS",
    "imageSrc": "skills2/sass-wordmark.svg"
  },
  {
    "title": "Bootstrap",
    "imageSrc": "skills2/bootstrap.svg"
  },
  {
    "title": "Tailwind",
    "imageSrc": "skills2/tailwindcss.svg"
  },
  {
    "title": "Material UI",
    "imageSrc": "skills2/materialui.svg"
  },
  {
    "title": "React",
    "imageSrc": "skills2/react.svg"
  },
  {
    "title": "Vue",
    "imageSrc": "skills2/vuejs.svg"
  },
  {
    "title": "TypeScript",
    "imageSrc": "skills2/typescript.svg"
  },
  {
    "title": "Node",
    "imageSrc": "skills2/nodejs.svg"
  },
  {
    "title": "PHP",
    "imageSrc": "skills2/php.svg"
  },
  {
    "title": "Python",
    "imageSrc": "skills2/python.svg"
  },  
  {
    "title": "Next",
    "imageSrc": "skills2/nextjs.svg"
  },
  {
    "title": "Astro",
    "imageSrc": "skills2/astro-light.svg"
  },
  {
    "title": "Laravel",
    "imageSrc": "skills2/laravel.svg"
  },
  {
    "title": "Django",
    "imageSrc": "skills2/django.svg"
  },
  {
    "title": "Drupal",
    "imageSrc": "skills2/drupal.svg"
  },
  {
    "title": "WordPress",
    "imageSrc": "skills2/wordpress.svg"
  },
  {
    "title": "Shopify",
    "imageSrc": "skills2/shopify.svg"
  },
  {
    "title": "HubSpot",
    "imageSrc": "skills2/hubspot.svg"
  },
  {
    "title": "Figma",
    "imageSrc": "skills2/figma.svg"
  },
  {
    "title": "Accessibility",
    "imageSrc": "skills2/accessibility-100.svg"
  }
]